apduboy/__init__.py
apduboy/bitcoin.py
apduboy/ethereum.py
apduboy/utils.py
apduboy/lib/__init__.py
apduboy/lib/bip32.py
apduboy-0.5.0.dist-info/LICENSE
apduboy-0.5.0.dist-info/METADATA
apduboy-0.5.0.dist-info/WHEEL
apduboy-0.5.0.dist-info/top_level.txt
apduboy-0.5.0.dist-info/RECORD
