Metadata-Version: 2.1
Name: apduboy
Version: 0.5.0
Summary: APDUs for Humans
Home-page: https://github.com/LedgerHQ/apduboy
Author: Anirudha Bose
Author-email: anirudha.bose@alumni.cern
License: MIT
Keywords: ledger apdu nano ethereum bitcoin
Platform: UNKNOWN
Classifier: Programming Language :: Python :: 3
Classifier: License :: OSI Approved :: MIT License
Classifier: Operating System :: OS Independent
Requires-Dist: construct (<=2.10.61)
Requires-Dist: rlp (<3,>=2)
Requires-Dist: ledgerwallet
Provides-Extra: dev
Requires-Dist: ipython ; extra == 'dev'
Requires-Dist: black ; extra == 'dev'
Requires-Dist: isort ; extra == 'dev'
Provides-Extra: test
Requires-Dist: pytest ; extra == 'test'
